shared_protocol/__init__.py
shared_protocol/base_model.py
shared_protocol/version.py
shared_protocol/command/__init__.py
shared_protocol/command/activate_slot.py
shared_protocol/command/base_command.py
shared_protocol/command/get_module_status.py
shared_protocol/enums/__init__.py
shared_protocol/enums/ack_type.py
shared_protocol/enums/command_type.py
shared_protocol/enums/event_type.py
shared_protocol/event/__init__.py
shared_protocol/event/base_event.py
shared_protocol/event/change_reported.py
shared_protocol/event/module_initialized.py
shared_protocol/event/module_status_received.py
shared_protocol/event/new_message_received.py
shared_protocol/event/sim_staus_received.py
shared_protocol/schemas/__init__.py
shared_protocol/schemas/common_response.py
shared_protocol/schemas/device_rebooted_ack.py
shared_protocol/schemas/reboot_device_command.py
shared_protocol-1.0.2.dist-info/METADATA
shared_protocol-1.0.2.dist-info/WHEEL
shared_protocol-1.0.2.dist-info/top_level.txt
shared_protocol-1.0.2.dist-info/RECORD
