Metadata-Version: 2.4
Name: shared-protocol
Version: 1.0.2
Summary: Shared protocol definitions for backend and hardware systems
Author-email: AmirHosein <a.khakbazzadeh@gmail.com>
Requires-Python: >=3.10
Requires-Dist: pydantic>=2.0
